<?xml version="1.0" encoding="UTF-8"?>
<window type="dialog" id="1121">
    <defaultcontrol always="true">7000</defaultcontrol>
	<menucontrol />
	<onunload condition="!String.IsEmpty(Window(home).Property(FanartType))">ClearProperty(FanartType,home)</onunload>
		<include>Animation_OpenClose_FadeZoom</include>
	<controls>
       		
	 <include content="ArtworkSlideshow">
		<param name="id" value="7000"/>
		<param name="pagecontrol_id" value="7060"/>
		<param name="artwork" value="$INFO[ListItem.Icon]"/>
		<include condition="![Container.Content(seasons) | Container.Content(episodes)]" content="ExtrafanartSource" />
		<include condition="[Container.Content(seasons) | Container.Content(episodes)]" content="ExtrafanartSource">
			<param name="prefix" value="tvshow." />
		</include>
		<include condition="[Container.Content(albums) | Container.Content(songs)]" content="ExtrafanartSource">
			<param name="prefix" value="artist." />
		</include>
		
	</include>
	
	</controls>
	
	
</window>