<?xml version="1.0" encoding="UTF-8"?>
<window type="window" id="1110">
	<backgroundcolor>FFFFFFFF</backgroundcolor>
	<menucontrol>9000</menucontrol>
	<defaultcontrol always="true">9000</defaultcontrol>
	<animation effect="fade" start="0" end="100" time="325">WindowOpenClose</animation>
	
		<!-- setproperty to came back,when nav to kodi windows (using replace window?,when property matching :true: in other windows) -->
		
			
	<controls>
	<!-- hardcoded templates/content panels 
	customizable colors,
	
	ids 
	
	*000 menucontrol bar top
		- search ?
		- player bar
	
	*000 menucontrol left (use static items, rather than use category path for better split)
		- grouplist items
		
				( check need set propoerty onfocus or, test against control.hasfocus(*001) as visible condition for 1110[**] containers )
		
		*001	- 'stöbern' : 
		*002		PVR Radio
		*003		PVR Radio channels
		*004		musicvideo					
					 videodb://musicvideos/
					
					grouplist
					*004(0) - content based onclick or onfocus id(*004) ?
					 [90040]
					
					1110[01]
						
								( PANEL 1 row CIRCLE LAYOUT )
					1110[02]
							RecentlyAddedMusicVideos 	videodb://recentlyaddedmusicvideos/
							
					1110[03]
							MusicVideoGenres 	videodb://musicvideos/genres/
								( PANEL 2 to 3 ROWs BANNER LAYOUT )
					
					1110[04]
							MusicVideoTitles 	videodb://musicvideos/titles/
								( PANEL 4 ROWs Landscape/thumb LAYOUT )
					1110[05]
							MusicVideoYears 	videodb://musicvideos/years/
								( PANEL 2 to 3 ROWs CIRCLE (NoTag,label center in circle) LAYOUT )
							
					1110[06]		
							MusicVideoArtists 	videodb://musicvideos/artists/
								( PANEL 6 to -10 ROWs CIRCLE ? SkinString? - Landscape? LAYOUT )
							
					1110[07]		
							MusicVideoAlbums 	videodb://musicvideos/albums/
								( PANEL 6 to -10 ROWs SQUARE ? SkinString? - Landscape? LAYOUT )
							
					1110[08]
							MusicVideoDirectors 	videodb://musicvideos/directors/
								( PANEL 1 row CIRCLE LAYOUT )
							
					1110[10]
							MusicVideoStudios 	videodb://musicvideos/studios/
								( PANEL 1 row SQAURE LAYOUT, LOGO ? resourceaddon exist ? )
							
								
  	 
				music nav
				playlists 	special://musicplaylists/ , special://skin/extras/playlists/musicvideos?
				addons
	
			- 'Currently'
				played
				added
				
			- ' my music'
				albums
				artists
				(songs)
				genres
				- 
	 -->
	 
	<!-- HUB HEADER BAR -->
	<control type="group">
		<height>100</height>
        <width>100%</width>
			
			<include content="bg_funwithcolors">
				<param name="layer1_top" value="darkblue" />
				<param name="layer1_bottom" value="ff000000" />
				<param name="layer2" value="black" />
				<param name="layer2_visible" value="false" />
			</include>
			
			
			
			<!-- Item Bar -->
			<control type="grouplist" id="100000">
				<top>10</top>
				<left>300</left>
				
				<orientation>horizontal</orientation>
				<usecontrolcoords>falase</usecontrolcoords>
				<itemgap>100</itemgap>
				<onleft>100000</onleft>
				<onright>100000</onright>
				<width>1600</width>
				
				<height>80</height>
			
			
			
			
				<control type="radiobutton" id="100001">
					<top>5</top>
					<height>60</height>
					<width>420</width>
			
					<radiowidth>30</radiowidth>
					<radioheight>35</radioheight>
					<radioposx>25</radioposx>
		
					<textureradioonfocus colordiffuse="white">hub/hub_search.png</textureradioonfocus>
					<textureradioonnofocus colordiffuse="grey">hub/hub_search.png</textureradioonnofocus>
					<textureradioofffocus colordiffuse="white">hub/hub_search.png</textureradioofffocus>
					<textureradiooffnofocus colordiffuse="grey">hub/hub_search.png</textureradiooffnofocus>
					
					
					<texturefocus colordiffuse="white">buttons/NF_1zu5.png</texturefocus>	
					<texturenofocus colordiffuse="44FFFFFF">buttons/button_6to1_Trans.png</texturenofocus>
					<font>MenucontrolItem</font>
					<textoffsetx>80</textoffsetx>
					<textoffsety>20</textoffsety>
					<textcolor>grey</textcolor>
					<focusedcolor>white</focusedcolor>
					<disabledcolor>green</disabledcolor>
					<invalidcolor>orange</invalidcolor>
					<textoffsetx>8</textoffsetx>
					<aligny>top</aligny>
					<pulseonselect>no</pulseonselect>
					<label>[I]S E A R C H   library[/I]....</label>
					<onclick>ActivateWindow(yesnodialog)</onclick>
				</control>
				<control type="label" id="$PARAM[id]">
					<height>1</height>
					<width>500</width>
					<font />
					<textcolor />
				</control>
				<control type="label" id="$PARAM[id]">
					<height>50</height>
					<width>500</width>
					<font>MenucontrolItem</font>
					<textcolor>white</textcolor>
					<label>thats the hub i will add more buttons</label>
				</control>
				
			</control>	
			
	
	</control>
	<!-- menuconrol left -->
	<control type="group">
		<height>100%</height>
        <width>300</width>
		<posy>100</posy>
			<!--
			perfect themed, try colors
			<control type="image">
				<texture>hub/diffuse_linear_vert_50_trans.png</texture>
				<bordertexture flipy="true" colordiffuse="ff000000">hub/diffuse_linear_vert.png</bordertexture>
				
				<colordiffuse>ff011222</colordiffuse>
				<aspectratio>stretch</aspectratio>
			</control>
			<control type="image">
				<texture flipy="true">hub/diffuse_linear_vert_50_trans.png</texture>
				<colordiffuse>FF080808</colordiffuse>
				<aspectratio>stretch</aspectratio>
			</control> -->
			
			<include content="bg_funwithcolors">
				<param name="layer2_visible" value="false" />
			</include>
			
			
			<control type="grouplist" id="9000">
				<description>widgets</description>
				<posx>10</posx>
				
				<onup>9000</onup>
				<ondown>9000</ondown>
				<onleft>5555</onleft>
				<onright>5555</onright>
				<orientation>vertical</orientation>
				<itemgap>10</itemgap>
				
				
				<include content="hub_sectionheader">
					<param name="id" value="01" />
					<param name="label" value="" />
				</include>
				
				
				<include content="hub_button">
					<param name="id" value="02" />
					<param name="action" value="" />
					<param name="label" value="test" />
					<param name="radio_icon" value="defaultaddonartistinfo.png" />
				</include>
				
				<include content="hub_button">
					<param name="id" value="03" />
					<param name="action" value="" />
					<param name="label" value="some" />
					<param name="radio_icon" value="defaultaddonartistinfo.png" />
				</include>
				
				<include content="hub_button">
					<param name="id" value="04" />
					<param name="action" value="" />
					<param name="label" value="things" />
					<param name="radio_icon" value="defaultaddonartistinfo.png" />
				</include>
				
				<include content="hub_button">
					<param name="id" value="05" />
					<param name="action" value="" />
					<param name="label" value="xy" />
					<param name="radio_icon" value="defaultaddonartistinfo.png" />
				</include>
				
				<include content="hub_button">
					<param name="id" value="06" />
					<param name="action" value="" />
					<param name="label" value="trfsvhbjk" />
					<param name="radio_icon" value="defaultaddonartistinfo.png" />
				</include>
				<include content="spacer_h">
					<param name="id" value="08" />
				</include>
				
				<include content="hub_sectionheader">
					<param name="id" value="09" />
					<param name="label" value="trfsvhbjk" />
				</include>
				
				
				<include content="hub_button">
					<param name="id" value="10" />
					<param name="action" value="" />
					<param name="label" value="trfsvhbjk" />
					<param name="radio_icon" value="defaultaddonartistinfo.png" />
				</include>
				
				<include content="hub_button">
					<param name="id" value="11" />
					<param name="action" value="" />
					<param name="label" value="trfsvhbjk" />
					<param name="radio_icon" value="defaultaddonartistinfo.png" />
				</include>
				
				<include content="hub_button">
					<param name="id" value="12" />
					<param name="action" value="" />
					<param name="label" value="trfsvhbjk" />
					<param name="radio_icon" value="defaultaddonartistinfo.png" />
				</include>
				
				<include content="hub_button">
					<param name="id" value="13" />
					<param name="action" value="" />
					<param name="label" value="trfsvhbjk" />
					<param name="radio_icon" value="defaultaddonartistinfo.png" />
				</include>
				
				<include content="spacer_h">
					<param name="id" value="66" />
					<param name="gap" value="200" />
				</include>
				
				<include content="hub_sectionheader">
					<param name="id" value="14" />
					<param name="label" value="trfsvhbjk" />
				</include>
				
				
				<include content="hub_button">
					<param name="id" value="15" />
					<param name="action" value="" />
					<param name="label" value="trfsvhbjk" />
					<param name="radio_icon" value="defaultaddonartistinfo.png" />
				</include>
				
				<include content="hub_button">
					<param name="id" value="22" />
					<param name="action" value="" />
					<param name="label" value="trfsvhbjk" />
					<param name="radio_icon" value="defaultaddonartistinfo.png" />
				</include>
				
				<include content="hub_button">
					<param name="id" value="23" />
					<param name="action" value="" />
					<param name="label" value="trfsvhbjk" />
					<param name="radio_icon" value="defaultaddonartistinfo.png" />
				</include>
				
				<include content="hub_button">
					<param name="id" value="24" />
					<param name="action" value="" />
					<param name="label" value="trfsvhbjk" />
					<param name="radio_icon" value="defaultaddonartistinfo.png" />
				</include>
				<include content="hub_button">
					<param name="id" value="25" />
					<param name="action" value="" />
					<param name="label" value="trfsvhbjk" />
					<param name="radio_icon" value="defaultaddonartistinfo.png" />
				</include>
				
				<include content="hub_button">
					<param name="id" value="26" />
					<param name="action" value="" />
					<param name="label" value="trfsvhbjk" />
					<param name="radio_icon" value="defaultaddonartistinfo.png" />
				</include>
				
				<include content="hub_button">
					<param name="id" value="27" />
					<param name="action" value="" />
					<param name="label" value="trfsvhbjk" />
					<param name="radio_icon" value="defaultaddonartistinfo.png" />
				</include>
				
				<include content="hub_button">
					<param name="id" value="28" />
					<param name="action" value="" />
					<param name="label" value="trfsvhbjk" />
					<param name="radio_icon" value="defaultaddonartistinfo.png" />
				</include>
				
				
			</control>
		</control>
		
		<!-- bg ccolor tintet artwork diffuse bg ? -->
			
		<control type="grouplist" id="5555">
			
			<top>150</top>
			<height>1000</height>
			<bottom>5</bottom>
				
				
			<left>350</left>
			<width>1520</width>
			<orientation>vertical</orientation>
			
			<usecontrolcoords>true</usecontrolcoords>
			<scrolltime tween="cubic" easing="in">300</scrolltime>
			<itemgap>-40</itemgap>
			
			<ondown>5555</ondown>
					
			<control type="group" id="5556">
				<description>1st row alignment correction</description>
				<height>-20</height>
			</control>
			
			<include content="Universal_ContainerHeader">
				<param name="groupid" value="6001" />
				<param name="id" value="5001" />
				<param name="label" value="$INFO[Skin.String(UserWidget1_name)]" />
				<visible>Control.IsVisible(5001)</visible>
			</include>
			
			<control type="panel" id="5001">
				<description>hardcoded content artist</description>
				<left>5</left>
				<width>1600</width>
				<height>800</height>
				
				<top>50</top>
				<preloaditems>2</preloaditems>
				<orientation>vertical</orientation>
				
				<onleft>9000</onleft>
				<onright>500160</onright>
				<onup>9000</onup>
				<ondown>5002</ondown>
				
				<scrolltime tween="quadratic">400</scrolltime>
				<autoscroll>true</autoscroll>
				
				<pagecontrol>500160</pagecontrol>
				<visible>[Integer.IsGreater(Container(5001).NumItems,0) | Container(5001).IsUpdating]</visible>
			
			
			
				<include>WidgetHome_landscape</include>
				
				<content limit="50">musicdb://artists/</content>
			</control>
			
			
			
			<include content="Widget_Container_Template" condition="Skin.HasSetting(UserWidget1_forceFixedlist)">
				<param name="type" value="fixedlist" />
				<param name="nr" value="1" />
				<param name="id" value="5001" />
				<param name="visible" value="Integer.IsGreater(Container(5001).NumItems,0) | Container(5001).IsUpdating" />
			</include>
			
			<include content="Universal_ContainerHeader">
				<param name="groupid" value="6002" />
				<param name="id" value="5002" />
				<param name="label" value="$INFO[Skin.String(UserWidget2_name)]" />
				<visible>Control.IsVisible(5002)</visible>
			</include>
			<include content="Widget_Container_Template" condition="!Skin.HasSetting(UserWidget2_forceFixedlist)">
				<param name="type" value="panel" />
				<param name="nr" value="2" />
				<param name="id" value="5002" />
				<param name="visible" value="Integer.IsGreater(Container(5002).NumItems,0) | Container(5002).IsUpdating" />
			</include>
			<include content="Widget_Container_Template" condition="Skin.HasSetting(UserWidget2_forceFixedlist)">
				<param name="type" value="fixedlist" />
				<param name="nr" value="2" />
				<param name="id" value="5002" />
				<param name="visible" value="Integer.IsGreater(Container(5002).NumItems,0) | Container(5002).IsUpdating" />
			</include>
			
			<include content="Universal_ContainerHeader">
				<param name="groupid" value="6003" />
				<param name="id" value="5003" />
				<param name="label" value="$INFO[Skin.String(UserWidget3_name)]" />
				<visible>Control.IsVisible(5003)</visible>
			</include>
			<include content="Widget_Container_Template" condition="!Skin.HasSetting(UserWidget3_forceFixedlist)">
				<param name="type" value="panel" />
				<param name="nr" value="3" />
				<param name="id" value="5003" />
				<param name="visible" value="Integer.IsGreater(Container(5003).NumItems,0) | Container(5003).IsUpdating" />
			</include>
			<include content="Widget_Container_Template" condition="Skin.HasSetting(UserWidget3_forceFixedlist)">
				<param name="type" value="fixedlist" />
				<param name="nr" value="3" />
				<param name="id" value="5003" />
				<param name="visible" value="Integer.IsGreater(Container(5003).NumItems,0) | Container(5003).IsUpdating" />
			</include>
			
			<include content="Universal_ContainerHeader">
				<param name="groupid" value="6004" />
				<param name="id" value="5004" />
				<param name="label" value="$INFO[Skin.String(UserWidget4_name)]" />
				<visible>Control.IsVisible(5004)</visible>
			</include>
			<include content="Widget_Container_Template" condition="!Skin.HasSetting(UserWidget4_forceFixedlist)">
				<param name="type" value="panel" />
				<param name="nr" value="4" />
				<param name="id" value="5004" />
				<param name="visible" value="Integer.IsGreater(Container(5004).NumItems,0) | Container(5004).IsUpdating" />
			</include>
			<include content="Widget_Container_Template" condition="Skin.HasSetting(UserWidget4_forceFixedlist)">
				<param name="type" value="fixedlist" />
				<param name="nr" value="4" />
				<param name="id" value="5004" />
				<param name="visible" value="Integer.IsGreater(Container(5004).NumItems,0) | Container(5004).IsUpdating" />
			</include>
			
			<include content="Universal_ContainerHeader">
				<param name="groupid" value="6005" />
				<param name="id" value="5005" />
				<param name="label" value="$INFO[Skin.String(UserWidget5_name)]" />
				<visible>Control.IsVisible(5005)</visible>
			</include>
			<include content="Widget_Container_Template" condition="!Skin.HasSetting(UserWidget5_forceFixedlist)">
				<param name="type" value="panel" />
				<param name="nr" value="5" />
				<param name="id" value="5005" />
				<param name="visible" value="Integer.IsGreater(Container(5005).NumItems,0) | Container(5005).IsUpdating" />
			</include>
			<include content="Widget_Container_Template" condition="Skin.HasSetting(UserWidget5_forceFixedlist)">
				<param name="type" value="fixedlist" />
				<param name="nr" value="5" />
				<param name="id" value="5005" />
				<param name="visible" value="Integer.IsGreater(Container(5005).NumItems,0) | Container(5005).IsUpdating" />
			</include>
			
			<include content="Universal_ContainerHeader">
				<param name="groupid" value="6006" />
				<param name="id" value="5006" />
				<param name="label" value="$INFO[Skin.String(UserWidget6_name)]" />
				<visible>Control.IsVisible(5006)</visible>
			</include>
			<include content="Widget_Container_Template" condition="!Skin.HasSetting(UserWidget6_forceFixedlist)">
				<param name="type" value="panel" />
				<param name="nr" value="6" />
				<param name="id" value="5006" />
				<param name="visible" value="Integer.IsGreater(Container(5006).NumItems,0) | Container(5006).IsUpdating" />
			</include>
			<include content="Widget_Container_Template" condition="Skin.HasSetting(UserWidget6_forceFixedlist)">
				<param name="type" value="fixedlist" />
				<param name="nr" value="6" />
				<param name="id" value="5006" />
				<param name="visible" value="Integer.IsGreater(Container(5006).NumItems,0) | Container(5006).IsUpdating" />
			</include>
			
			<include content="Universal_ContainerHeader">
				<param name="groupid" value="6007" />
				<param name="id" value="5007" />
				<param name="label" value="$INFO[Skin.String(UserWidget7_name)]" />
				<visible>Control.IsVisible(5007)</visible>
			</include>
			<include content="Widget_Container_Template" condition="!Skin.HasSetting(UserWidget7_forceFixedlist)">
				<param name="type" value="panel" />
				<param name="nr" value="7" />
				<param name="id" value="5007" />
				<param name="visible" value="Integer.IsGreater(Container(5007).NumItems,0) | Container(5007).IsUpdating" />
			</include>
			<include content="Widget_Container_Template" condition="Skin.HasSetting(UserWidget7_forceFixedlist)">
				<param name="type" value="fixedlist" />
				<param name="nr" value="7" />
				<param name="id" value="5007" />
				<param name="visible" value="Integer.IsGreater(Container(5007).NumItems,0) | Container(5007).IsUpdating" />
			</include>
			
			<include content="Universal_ContainerHeader">
				<param name="groupid" value="6008" />
				<param name="id" value="5008" />
				<param name="label" value="$INFO[Skin.String(UserWidget8_name)]" />
				<visible>Control.IsVisible(5008)</visible>
			</include>
			<include content="Widget_Container_Template" condition="!Skin.HasSetting(UserWidget8_forceFixedlist)">
				<param name="type" value="panel" />
				<param name="nr" value="8" />
				<param name="id" value="5008" />
				<param name="visible" value="Integer.IsGreater(Container(5008).NumItems,0) | Container(5008).IsUpdating" />
			</include>
			<include content="Widget_Container_Template" condition="Skin.HasSetting(UserWidget8_forceFixedlist)">
				<param name="type" value="fixedlist" />
				<param name="nr" value="8" />
				<param name="id" value="5008" />
				<param name="visible" value="Integer.IsGreater(Container(5008).NumItems,0) | Container(5008).IsUpdating" />
			</include>
			
			<include content="Universal_ContainerHeader">
				<param name="groupid" value="6009" />
				<param name="id" value="5009" />
				<param name="label" value="$INFO[Skin.String(UserWidget9_name)]" />
				<visible>Control.IsVisible(5009)</visible>
			</include>
			<include content="Widget_Container_Template" condition="!Skin.HasSetting(UserWidget9_forceFixedlist)">
				<param name="type" value="panel" />
				<param name="nr" value="9" />
				<param name="id" value="5009" />
				<param name="visible" value="Integer.IsGreater(Container(5009).NumItems,0) | Container(5009).IsUpdating" />
			</include>
			<include content="Widget_Container_Template" condition="Skin.HasSetting(UserWidget9_forceFixedlist)">
				<param name="type" value="fixedlist" />
				<param name="nr" value="9" />
				<param name="id" value="5009" />
				<param name="visible" value="Integer.IsGreater(Container(5009).NumItems,0) | Container(5009).IsUpdating" />
			</include>
			
			<include content="Universal_ContainerHeader">
				<param name="groupid" value="6010" />
				<param name="id" value="5010" />
				<param name="label" value="$INFO[Skin.String(UserWidget10_name)]" />
				<visible>Control.IsVisible(5010)</visible>
			</include>
			<include content="Widget_Container_Template" condition="!Skin.HasSetting(UserWidget10_forceFixedlist)">
				<param name="type" value="panel" />
				<param name="nr" value="10" />
				<param name="id" value="5010" />
				<param name="visible" value="Integer.IsGreater(Container(5010).NumItems,0) | Container(5010).IsUpdating" />
			</include>
			<include content="Widget_Container_Template" condition="Skin.HasSetting(UserWidget10_forceFixedlist)">
				<param name="type" value="fixedlist" />
				<param name="nr" value="10" />
				<param name="id" value="5010" />
				<param name="visible" value="Integer.IsGreater(Container(5010).NumItems,0) | Container(5010).IsUpdating" />
			</include>
	
			<include content="Universal_ContainerHeader">
				<param name="groupid" value="6011" />
				<param name="id" value="5011" />
				<param name="label" value="$INFO[Skin.String(UserWidget11_name)]" />
				<visible>Control.IsVisible(5011)</visible>
			</include>
			<include content="Widget_Container_Template" condition="!Skin.HasSetting(UserWidget11_forceFixedlist)">
				<param name="type" value="panel" />
				<param name="nr" value="11" />
				<param name="id" value="5011" />
				<param name="visible" value="Integer.IsGreater(Container(5011).NumItems,0) | Container(5011).IsUpdating" />
			</include>
			<include content="Widget_Container_Template" condition="Skin.HasSetting(UserWidget11_forceFixedlist)">
				<param name="type" value="fixedlist" />
				<param name="nr" value="11" />
				<param name="id" value="5011" />
				<param name="visible" value="Integer.IsGreater(Container(5011).NumItems,0) | Container(5011).IsUpdating" />
			</include>
			
			<include content="Universal_ContainerHeader">
				<param name="groupid" value="6012" />
				<param name="id" value="5012" />
				<param name="label" value="$INFO[Skin.String(UserWidget12_name)]" />
				<visible>Control.IsVisible(5012)</visible>
			</include>
			<include content="Widget_Container_Template" condition="!Skin.HasSetting(UserWidget12_forceFixedlist)">
				<param name="type" value="panel" />
				<param name="nr" value="12" />
				<param name="id" value="5012" />
				<param name="visible" value="Integer.IsGreater(Container(5012).NumItems,0) | Container(5012).IsUpdating" />
			</include>
			<include content="Widget_Container_Template" condition="Skin.HasSetting(UserWidget12_forceFixedlist)">
				<param name="type" value="fixedlist" />
				<param name="nr" value="12" />
				<param name="id" value="5012" />
				<param name="visible" value="Integer.IsGreater(Container(5012).NumItems,0) | Container(5012).IsUpdating" />
			</include>
			
			<include content="Universal_ContainerHeader">
				<param name="groupid" value="6013" />
				<param name="id" value="5013" />
				<param name="label" value="$INFO[Skin.String(UserWidget13_name)]" />
				<visible>Control.IsVisible(5013)</visible>
			</include>
			<include content="Widget_Container_Template" condition="!Skin.HasSetting(UserWidget13_forceFixedlist)">
				<param name="type" value="panel" />
				<param name="nr" value="13" />
				<param name="id" value="5013" />
				<param name="visible" value="Integer.IsGreater(Container(5013).NumItems,0) | Container(5013).IsUpdating" />
			</include>
			<include content="Widget_Container_Template" condition="Skin.HasSetting(UserWidget13_forceFixedlist)">
				<param name="type" value="fixedlist" />
				<param name="nr" value="13" />
				<param name="id" value="5013" />
				<param name="visible" value="Integer.IsGreater(Container(5013).NumItems,0) | Container(5013).IsUpdating" />
			</include>
			
			<include content="Universal_ContainerHeader">
				<param name="groupid" value="6014" />
				<param name="id" value="5014" />
				<param name="label" value="$INFO[Skin.String(UserWidget14_name)]" />
				<visible>Control.IsVisible(5014)</visible>
			</include>
			<include content="Widget_Container_Template" condition="!Skin.HasSetting(UserWidget14_forceFixedlist)">
				<param name="type" value="panel" />
				<param name="nr" value="14" />
				<param name="id" value="5014" />
				<param name="visible" value="Integer.IsGreater(Container(5014).NumItems,0) | Container(5014).IsUpdating" />
			</include>
			<include content="Widget_Container_Template" condition="Skin.HasSetting(UserWidget14_forceFixedlist)">
				<param name="type" value="fixedlist" />
				<param name="nr" value="14" />
				<param name="id" value="5014" />
				<param name="visible" value="Integer.IsGreater(Container(5014).NumItems,0) | Container(5014).IsUpdating" />
			</include>
			
			<include content="Universal_ContainerHeader">
				<param name="groupid" value="6015" />
				<param name="id" value="5015" />
				<param name="label" value="$INFO[Skin.String(UserWidget15_name)]" />
				<visible>Control.IsVisible(5015)</visible>
			</include>
			<include content="Widget_Container_Template" condition="!Skin.HasSetting(UserWidget15_forceFixedlist)">
				<param name="type" value="panel" />
				<param name="nr" value="15" />
				<param name="id" value="5015" />
				<param name="visible" value="Integer.IsGreater(Container(5015).NumItems,0) | Container(5015).IsUpdating" />
			</include>
			<include content="Widget_Container_Template" condition="Skin.HasSetting(UserWidget15_forceFixedlist)">
				<param name="type" value="fixedlist" />
				<param name="nr" value="15" />
				<param name="id" value="5015" />
				<param name="visible" value="Integer.IsGreater(Container(5015).NumItems,0) | Container(5005).IsUpdating" />
			</include>
			
			<include content="Universal_ContainerHeader">
				<param name="groupid" value="6016" />
				<param name="id" value="5016" />
				<param name="label" value="$INFO[Skin.String(UserWidget16_name)]" />
				<visible>Control.IsVisible(5016)</visible>
			</include>
			<include content="Widget_Container_Template" condition="!Skin.HasSetting(UserWidget16_forceFixedlist)">
				<param name="type" value="panel" />
				<param name="nr" value="16" />
				<param name="id" value="5016" />
				<param name="visible" value="Integer.IsGreater(Container(5016).NumItems,0) | Container(5016).IsUpdating" />
			</include>
			<include content="Widget_Container_Template" condition="Skin.HasSetting(UserWidget16_forceFixedlist)">
				<param name="type" value="fixedlist" />
				<param name="nr" value="16" />
				<param name="id" value="5016" />
				<param name="visible" value="Integer.IsGreater(Container(5016).NumItems,0) | Container(5016).IsUpdating" />
			</include>
			
			<include content="Universal_ContainerHeader">
				<param name="groupid" value="6017" />
				<param name="id" value="5017" />
				<param name="label" value="$INFO[Skin.String(UserWidget17_name)]" />
				<visible>Control.IsVisible(5017)</visible>
			</include>
			<include content="Widget_Container_Template" condition="!Skin.HasSetting(UserWidget17_forceFixedlist)">
				<param name="type" value="panel" />
				<param name="nr" value="7" />
				<param name="id" value="5017" />
				<param name="visible" value="Integer.IsGreater(Container(5017).NumItems,0) | Container(5017).IsUpdating" />
			</include>
			<include content="Widget_Container_Template" condition="Skin.HasSetting(UserWidget17_forceFixedlist)">
				<param name="type" value="fixedlist" />
				<param name="nr" value="7" />
				<param name="id" value="5017" />
				<param name="visible" value="Integer.IsGreater(Container(5017).NumItems,0) | Container(5017).IsUpdating" />
			</include>
			
			<include content="Universal_ContainerHeader">
				<param name="groupid" value="6018" />
				<param name="id" value="5018" />
				<param name="label" value="$INFO[Skin.String(UserWidget18_name)]" />
				<visible>Control.IsVisible(5018)</visible>
			</include>
			<include content="Widget_Container_Template" condition="!Skin.HasSetting(UserWidget18_forceFixedlist)">
				<param name="type" value="panel" />
				<param name="nr" value="18" />
				<param name="id" value="5018" />
				<param name="visible" value="Integer.IsGreater(Container(5018).NumItems,0) | Container(5018).IsUpdating" />
			</include>
			<include content="Widget_Container_Template" condition="Skin.HasSetting(UserWidget18_forceFixedlist)">
				<param name="type" value="fixedlist" />
				<param name="nr" value="18" />
				<param name="id" value="5018" />
				<param name="visible" value="Integer.IsGreater(Container(5018).NumItems,0) | Container(5018).IsUpdating" />
			</include>
			
			<include content="Universal_ContainerHeader">
				<param name="groupid" value="6019" />
				<param name="id" value="5019" />
				<param name="label" value="$INFO[Skin.String(UserWidget19_name)]" />
				<visible>Control.IsVisible(5019)</visible>
			</include>
			<include content="Widget_Container_Template" condition="!Skin.HasSetting(UserWidget19_forceFixedlist)">
				<param name="type" value="panel" />
				<param name="nr" value="19" />
				<param name="id" value="5019" />
				<param name="visible" value="Integer.IsGreater(Container(5019).NumItems,0) | Container(5019).IsUpdating" />
			</include>
			<include content="Widget_Container_Template" condition="Skin.HasSetting(UserWidget19_forceFixedlist)">
				<param name="type" value="fixedlist" />
				<param name="nr" value="19" />
				<param name="id" value="5019" />
				<param name="visible" value="Integer.IsGreater(Container(5019).NumItems,0) | Container(5019).IsUpdating" />
			</include>
			
			<include content="Universal_ContainerHeader">
				<param name="groupid" value="6020" />
				<param name="id" value="5020" />
				<param name="label" value="$INFO[Skin.String(UserWidget20_name)]" />
				<visible>Control.IsVisible(5020)</visible>
			</include>
			<include content="Widget_Container_Template" condition="!Skin.HasSetting(UserWidget20_forceFixedlist)">
				<param name="type" value="panel" />
				<param name="nr" value="20" />
				<param name="id" value="5020" />
				<param name="visible" value="Integer.IsGreater(Container(5020).NumItems,0) | Container(5020).IsUpdating" />
			</include>
			<include content="Widget_Container_Template" condition="Skin.HasSetting(UserWidget20_forceFixedlist)">
				<param name="type" value="fixedlist" />
				<param name="nr" value="20" />
				<param name="id" value="5020" />
				<param name="visible" value="Integer.IsGreater(Container(5020).NumItems,0) | Container(5020).IsUpdating" />
			</include>
			
			<include content="Universal_ContainerHeader">
				<param name="groupid" value="6021" />
				<param name="id" value="5021" />
				<param name="label" value="$INFO[Skin.String(UserWidget21_name)]" />
				<visible>Control.IsVisible(5021)</visible>
			</include>
			<include content="Widget_Container_Template" condition="!Skin.HasSetting(UserWidget21_forceFixedlist)">
				<param name="type" value="panel" />
				<param name="nr" value="21" />
				<param name="id" value="5021" />
				<param name="visible" value="Integer.IsGreater(Container(5021).NumItems,0) | Container(5021).IsUpdating" />
			</include>
			<include content="Widget_Container_Template" condition="Skin.HasSetting(UserWidget21_forceFixedlist)">
				<param name="type" value="fixedlist" />
				<param name="nr" value="21" />
				<param name="id" value="5021" />
				<param name="visible" value="Integer.IsGreater(Container(5021).NumItems,0) | Container(5021).IsUpdating" />
			</include>
			
			<include content="Universal_ContainerHeader">
				<param name="groupid" value="6022" />
				<param name="id" value="5022" />
				<param name="label" value="$INFO[Skin.String(UserWidget22_name)]" />
				<visible>Control.IsVisible(5022)</visible>
			</include>
			<include content="Widget_Container_Template" condition="!Skin.HasSetting(UserWidget22_forceFixedlist)">
				<param name="type" value="panel" />
				<param name="nr" value="22" />
				<param name="id" value="5022" />
				<param name="visible" value="Integer.IsGreater(Container(5022).NumItems,0) | Container(5022).IsUpdating" />
			</include>
			<include content="Widget_Container_Template" condition="Skin.HasSetting(UserWidget22_forceFixedlist)">
				<param name="type" value="fixedlist" />
				<param name="nr" value="22" />
				<param name="id" value="5022" />
				<param name="visible" value="Integer.IsGreater(Container(5022).NumItems,0) | Container(5022).IsUpdating" />
			</include>
			
			<include content="Universal_ContainerHeader">
				<param name="groupid" value="6023" />
				<param name="id" value="5023" />
				<param name="label" value="$INFO[Skin.String(UserWidget23_name)]" />
				<visible>Control.IsVisible(5023)</visible>
			</include>
			<include content="Widget_Container_Template" condition="!Skin.HasSetting(UserWidget23_forceFixedlist)">
				<param name="type" value="panel" />
				<param name="nr" value="23" />
				<param name="id" value="5023" />
				<param name="visible" value="Integer.IsGreater(Container(5023).NumItems,0) | Container(5023).IsUpdating" />
			</include>
			<include content="Widget_Container_Template" condition="Skin.HasSetting(UserWidget23_forceFixedlist)">
				<param name="type" value="fixedlist" />
				<param name="nr" value="23" />
				<param name="id" value="5023" />
				<param name="visible" value="Integer.IsGreater(Container(5023).NumItems,0) | Container(5023).IsUpdating" />
			</include>
			
			<include content="Universal_ContainerHeader">
				<param name="groupid" value="6024" />
				<param name="id" value="5024" />
				<param name="label" value="$INFO[Skin.String(UserWidget24_name)]" />
				<visible>Control.IsVisible(5024)</visible>
			</include>
			<include content="Widget_Container_Template" condition="!Skin.HasSetting(UserWidget24_forceFixedlist)">
				<param name="type" value="panel" />
				<param name="nr" value="24" />
				<param name="id" value="5024" />
				<param name="visible" value="Integer.IsGreater(Container(5024).NumItems,0) | Container(5024).IsUpdating" />
			</include>
			<include content="Widget_Container_Template" condition="Skin.HasSetting(UserWidget24_forceFixedlist)">
				<param name="type" value="fixedlist" />
				<param name="nr" value="24" />
				<param name="id" value="5024" />
				<param name="visible" value="Integer.IsGreater(Container(5024).NumItems,0) | Container(5024).IsUpdating" />
			</include>
			
			<include content="Universal_ContainerHeader">
				<param name="groupid" value="6025" />
				<param name="id" value="5025" />
				<param name="label" value="$INFO[Skin.String(UserWidget25_name)]" />
				<visible>Control.IsVisible(5025)</visible>
			</include>
			<include content="Widget_Container_Template" condition="!Skin.HasSetting(UserWidget25_forceFixedlist)">
				<param name="type" value="panel" />
				<param name="nr" value="25" />
				<param name="id" value="5025" />
				<param name="visible" value="Integer.IsGreater(Container(5025).NumItems,0) | Container(5025).IsUpdating" />
			</include>
			<include content="Widget_Container_Template" condition="Skin.HasSetting(UserWidget25_forceFixedlist)">
				<param name="type" value="fixedlist" />
				<param name="nr" value="25" />
				<param name="id" value="5025" />
				<param name="visible" value="Integer.IsGreater(Container(5025).NumItems,0) | Container(5005).IsUpdating" />
			</include>
			
			<include content="Universal_ContainerHeader">
				<param name="groupid" value="6026" />
				<param name="id" value="5026" />
				<param name="label" value="$INFO[Skin.String(UserWidget26_name)]" />
				<visible>Control.IsVisible(5026)</visible>
			</include>
			<include content="Widget_Container_Template" condition="!Skin.HasSetting(UserWidget26_forceFixedlist)">
				<param name="type" value="panel" />
				<param name="nr" value="26" />
				<param name="id" value="5026" />
				<param name="visible" value="Integer.IsGreater(Container(5026).NumItems,0) | Container(5026).IsUpdating" />
			</include>
			<include content="Widget_Container_Template" condition="Skin.HasSetting(UserWidget26_forceFixedlist)">
				<param name="type" value="fixedlist" />
				<param name="nr" value="26" />
				<param name="id" value="5026" />
				<param name="visible" value="Integer.IsGreater(Container(5026).NumItems,0) | Container(5026).IsUpdating" />
			</include>
			
			<include content="Universal_ContainerHeader">
				<param name="groupid" value="6027" />
				<param name="id" value="5027" />
				<param name="label" value="$INFO[Skin.String(UserWidget27_name)]" />
				<visible>Control.IsVisible(5027)</visible>
			</include>
			<include content="Widget_Container_Template" condition="!Skin.HasSetting(UserWidget27_forceFixedlist)">
				<param name="type" value="panel" />
				<param name="nr" value="27" />
				<param name="id" value="5027" />
				<param name="visible" value="Integer.IsGreater(Container(5027).NumItems,0) | Container(5027).IsUpdating" />
			</include>
			<include content="Widget_Container_Template" condition="Skin.HasSetting(UserWidget27_forceFixedlist)">
				<param name="type" value="fixedlist" />
				<param name="nr" value="27" />
				<param name="id" value="5027" />
				<param name="visible" value="Integer.IsGreater(Container(5027).NumItems,0) | Container(5027).IsUpdating" />
			</include>
			
			<include content="Universal_ContainerHeader">
				<param name="groupid" value="6028" />
				<param name="id" value="5028" />
				<param name="label" value="$INFO[Skin.String(UserWidget28_name)]" />
				<visible>Control.IsVisible(5028)</visible>
			</include>
			<include content="Widget_Container_Template" condition="!Skin.HasSetting(UserWidget28_forceFixedlist)">
				<param name="type" value="panel" />
				<param name="nr" value="28" />
				<param name="id" value="5028" />
				<param name="visible" value="Integer.IsGreater(Container(5028).NumItems,0) | Container(5028).IsUpdating" />
			</include>
			<include content="Widget_Container_Template" condition="Skin.HasSetting(UserWidget28_forceFixedlist)">
				<param name="type" value="fixedlist" />
				<param name="nr" value="28" />
				<param name="id" value="5028" />
				<param name="visible" value="Integer.IsGreater(Container(5028).NumItems,0) | Container(5028).IsUpdating" />
			</include>
			
			<include content="Universal_ContainerHeader">
				<param name="groupid" value="6029" />
				<param name="id" value="5029" />
				<param name="label" value="$INFO[Skin.String(UserWidget29_name)]" />
				<visible>Control.IsVisible(5029)</visible>
			</include>
			<include content="Widget_Container_Template" condition="!Skin.HasSetting(UserWidget29_forceFixedlist)">
				<param name="type" value="panel" />
				<param name="nr" value="29" />
				<param name="id" value="5029" />
				<param name="visible" value="Integer.IsGreater(Container(5029).NumItems,0) | Container(5029).IsUpdating" />
			</include>
			<include content="Widget_Container_Template" condition="Skin.HasSetting(UserWidget29_forceFixedlist)">
				<param name="type" value="fixedlist" />
				<param name="nr" value="29" />
				<param name="id" value="5029" />
				<param name="visible" value="Integer.IsGreater(Container(5029).NumItems,0) | Container(5029).IsUpdating" />
			</include>
			
			<include content="Universal_ContainerHeader">
				<param name="groupid" value="6030" />
				<param name="id" value="5030" />
				<param name="label" value="$INFO[Skin.String(UserWidget30_name)]" />
				<visible>Control.IsVisible(5030)</visible>
			</include>
			<include content="Widget_Container_Template" condition="!Skin.HasSetting(UserWidget30_forceFixedlist)">
				<param name="type" value="panel" />
				<param name="nr" value="30" />
				<param name="id" value="5030" />
				<param name="visible" value="Integer.IsGreater(Container(5030).NumItems,0) | Container(5030).IsUpdating" />
			</include>
			<include content="Widget_Container_Template" condition="Skin.HasSetting(UserWidget30_forceFixedlist)">
				<param name="type" value="fixedlist" />
				<param name="nr" value="30" />
				<param name="id" value="5030" />
				<param name="visible" value="Integer.IsGreater(Container(5030).NumItems,0) | Container(5030).IsUpdating" />
			</include>
		</control>
		
		<control type="scrollbar" id="500160">
			<right>10</right>
			<top>180</top>
			
			<onup>500160</onup>
			<ondown>500160</ondown>
			
			<onleft>5001</onleft>
			<height>800</height>
		</control>
	
	</controls>
</window>